{
  "study_id": "S04j",
  "ticket_id": "1781069571.719.463e18dd",
  "worker": "testbeam-laptop-4",
  "title": "pathology-interaction calibrated veto transfer",
  "raw_root_dir": "data/root/root",
  "output_dir": "reports/1781069571.719.463e18dd__s04j_pathology_interaction_calibrated_veto_transfer",
  "random_seed": 20260611,
  "amplitude_cut_adc": 1000.0,
  "baseline_samples": [0, 1, 2, 3],
  "samples_per_channel": 18,
  "sample_period_ns": 10.0,
  "cfd_fraction": 0.2,
  "tof_per_cm_ns": 0.078,
  "spacing_cm": 2.0,
  "staves": {
    "B2": 0,
    "B4": 2,
    "B6": 4,
    "B8": 6
  },
  "run_groups": {
    "sample_i_calib": [31, 32, 33, 34, 35, 36, 37, 39, 40, 41, 42],
    "sample_i_analysis": [44, 45, 46, 47, 48, 49, 50, 51, 52, 53, 54, 55, 56, 57],
    "sample_ii_calib": [64],
    "sample_ii_analysis": [58, 59, 60, 61, 62, 63, 65]
  },
  "timing": {
    "train_runs": [31, 32, 33, 34, 35, 36, 37, 39, 40, 41, 42, 64],
    "heldout_runs": [58, 59, 60, 61, 62, 63, 65],
    "downstream_staves": ["B4", "B6", "B8"],
    "external_staves": ["B2", "B4", "B6", "B8"]
  },
  "expected": {
    "selected_pulses_total": 640737,
    "sample_ii_analysis_selected_pulses": 125096,
    "run64_selected_pulses": 14630,
    "run64_all_hit_events": 207,
    "heldout_all_hit_events": 3774
  },
  "traditional": {
    "ridge_alphas": [0.1, 1.0, 10.0, 100.0, 1000.0],
    "feature_sets": ["amp_poly_by_stave", "amp_bin_by_stave"],
    "amplitude_edges_adc": [1000, 1500, 2200, 3200, 4700, 6800, 10000, 15000, 25000]
  },
  "models": {
    "ridge_alphas": [0.1, 1.0, 10.0, 100.0],
    "hgb_max_iter": [80],
    "hgb_max_leaf_nodes": [15, 31],
    "hgb_learning_rate": [0.06],
    "mlp_hidden": [24],
    "nn_epochs": 12,
    "nn_batch_size": 256,
    "cnn_channels": [8],
    "gated_hidden": [16]
  },
  "veto": {
    "target_acceptance": 0.95,
    "minimum_supported_acceptance": 0.90,
    "max_support_drift": 0.10,
    "tail_threshold_ns": 5.0
  },
  "bootstrap_iterations": 1500,
  "tail_threshold_ns": 5.0
}
